README.md
setup.py
tkinter_game/__init__.py
tkinter_game/main.py
tkinter_game.egg-info/PKG-INFO
tkinter_game.egg-info/SOURCES.txt
tkinter_game.egg-info/dependency_links.txt
tkinter_game.egg-info/top_level.txt