Metadata-Version: 2.1
Name: tkinter-game
Version: 0.2.1
Summary: 基于Tkinter的小游戏框架
License: MIT Licence
